mcp_demo/__init__.py
mcp_demo/server.py
mcp_demo-0.1.0.dist-info/METADATA
mcp_demo-0.1.0.dist-info/WHEEL
mcp_demo-0.1.0.dist-info/entry_points.txt
mcp_demo-0.1.0.dist-info/RECORD
