Metadata-Version: 2.4
Name: mcp-demo
Version: 0.1.0
Summary: A MCP server project
Author-email: DevinWu <wuhaifengdhu@gmail.com>
Requires-Python: >=3.12
Requires-Dist: mcp>=1.7.1
